pathological/Path.py
pathological/__init__.py
pathological-0.0.11.dist-info/LICENSE
pathological-0.0.11.dist-info/METADATA
pathological-0.0.11.dist-info/WHEEL
pathological-0.0.11.dist-info/top_level.txt
pathological-0.0.11.dist-info/RECORD
